odoo/addons/sale_operating_unit/README.rst
odoo/addons/sale_operating_unit/__init__.py
odoo/addons/sale_operating_unit/__manifest__.py
odoo/addons/sale_operating_unit/i18n/it.po
odoo/addons/sale_operating_unit/i18n/sale_operating_unit.pot
odoo/addons/sale_operating_unit/models/__init__.py
odoo/addons/sale_operating_unit/models/crm_team.py
odoo/addons/sale_operating_unit/models/sale_order.py
odoo/addons/sale_operating_unit/readme/CONTRIBUTORS.md
odoo/addons/sale_operating_unit/readme/DESCRIPTION.md
odoo/addons/sale_operating_unit/readme/ROADMAP.md
odoo/addons/sale_operating_unit/readme/USAGE.md
odoo/addons/sale_operating_unit/report/__init__.py
odoo/addons/sale_operating_unit/report/sale_report.py
odoo/addons/sale_operating_unit/security/sale_security.xml
odoo/addons/sale_operating_unit/static/description/icon.png
odoo/addons/sale_operating_unit/static/description/index.html
odoo/addons/sale_operating_unit/tests/__init__.py
odoo/addons/sale_operating_unit/tests/test_sale_operating_unit.py
odoo/addons/sale_operating_unit/views/sale_report_view.xml
odoo/addons/sale_operating_unit/views/sale_view.xml
odoo_addon_sale_operating_unit-18.0.1.0.0.2.dist-info/METADATA
odoo_addon_sale_operating_unit-18.0.1.0.0.2.dist-info/WHEEL
odoo_addon_sale_operating_unit-18.0.1.0.0.2.dist-info/top_level.txt
odoo_addon_sale_operating_unit-18.0.1.0.0.2.dist-info/RECORD
